pyaws_s3/__init__.py
pyaws_s3/s3.py
pyaws_s3-1.0.28.dist-info/licenses/LICENSE.md
pyaws_s3-1.0.28.dist-info/METADATA
pyaws_s3-1.0.28.dist-info/WHEEL
pyaws_s3-1.0.28.dist-info/top_level.txt
pyaws_s3-1.0.28.dist-info/RECORD
