Metadata-Version: 2.4
Name: pyaws-s3
Version: 1.0.28
Summary: A Python package for AWS S3 utilities
Author-email: Giuseppe Zileni <giuseppe.zileni@gmail.com>
Keywords: aws,s3,utilities
Classifier: Programming Language :: Python :: 3
Classifier: Operating System :: OS Independent
Requires-Python: >=3.9
License-File: LICENSE.md
Requires-Dist: aioboto3>=14.3.0
Requires-Dist: aiobotocore>=2.22.0
Requires-Dist: aiofiles>=24.1.0
Requires-Dist: aiohappyeyeballs>=2.6.1
Requires-Dist: aiohttp>=3.11.18
Requires-Dist: aioitertools>=0.12.0
Requires-Dist: aiosignal>=1.3.2
Requires-Dist: attrs>=25.3.0
Requires-Dist: boto3>=1.37.3
Requires-Dist: botocore>=1.37.3
Requires-Dist: build>=1.2.2.post1
Requires-Dist: chardet>=5.2.0
Requires-Dist: contourpy>=1.3.2
Requires-Dist: cycler>=0.12.1
Requires-Dist: fonttools>=4.58.0
Requires-Dist: fpdf>=1.7.2
Requires-Dist: frozenlist>=1.6.0
Requires-Dist: idna>=3.10
Requires-Dist: iniconfig>=2.1.0
Requires-Dist: jmespath>=1.0.1
Requires-Dist: kiwisolver>=1.4.8
Requires-Dist: matplotlib>=3.10.3
Requires-Dist: multidict>=6.4.3
Requires-Dist: narwhals>=1.39.1
Requires-Dist: packaging>=23.2
Requires-Dist: pandas>=2.2.3
Requires-Dist: pillow>=11.2.1
Requires-Dist: plotly>=6.1.0
Requires-Dist: pluggy>=1.6.0
Requires-Dist: propcache>=0.3.1
Requires-Dist: pyparsing>=3.2.3
Requires-Dist: pyproject_hooks>=1.2.0
Requires-Dist: pytest>=8.3.5
Requires-Dist: python-dateutil>=2.9.0.post0
Requires-Dist: pytz>=2025.2
Requires-Dist: reportlab>=4.4.1
Requires-Dist: s3transfer>=0.11.3
Requires-Dist: setuptools>=80.7.1
Requires-Dist: six>=1.17.0
Requires-Dist: tzdata>=2025.2
Requires-Dist: urllib3>=2.4.0
Requires-Dist: wrapt>=1.17.2
Requires-Dist: yarl>=1.20.0
Dynamic: license-file
